{
  "AWSTemplateFormatVersion": "2010-09-09",
  "Description": "The AWS CloudFormation template for this Serverless application",
  "Resources": {
    "ServerlessDeploymentBucket": {
      "Type": "AWS::S3::Bucket",
      "Properties": {
        "BucketEncryption": {
          "ServerSideEncryptionConfiguration": [
            {
              "ServerSideEncryptionByDefault": {
                "SSEAlgorithm": "AES256"
              }
            }
          ]
        }
      }
    },
    "ServerlessDeploymentBucketPolicy": {
      "Type": "AWS::S3::BucketPolicy",
      "Properties": {
        "Bucket": {
          "Ref": "ServerlessDeploymentBucket"
        },
        "PolicyDocument": {
          "Statement": [
            {
              "Action": "s3:*",
              "Effect": "Deny",
              "Principal": "*",
              "Resource": [
                {
                  "Fn::Join": [
                    "",
                    [
                      "arn:",
                      {
                        "Ref": "AWS::Partition"
                      },
                      ":s3:::",
                      {
                        "Ref": "ServerlessDeploymentBucket"
                      },
                      "/*"
                    ]
                  ]
                },
                {
                  "Fn::Join": [
                    "",
                    [
                      "arn:",
                      {
                        "Ref": "AWS::Partition"
                      },
                      ":s3:::",
                      {
                        "Ref": "ServerlessDeploymentBucket"
                      }
                    ]
                  ]
                }
              ],
              "Condition": {
                "Bool": {
                  "aws:SecureTransport": false
                }
              }
            }
          ]
        }
      }
    },
    "RepositoryWatcherLogGroup": {
      "Type": "AWS::Logs::LogGroup",
      "Properties": {
        "LogGroupName": "/aws/lambda/github-dev-repositoryWatcher"
      }
    },
    "IamRoleLambdaExecution": {
      "Type": "AWS::IAM::Role",
      "Properties": {
        "AssumeRolePolicyDocument": {
          "Version": "2012-10-17",
          "Statement": [
            {
              "Effect": "Allow",
              "Principal": {
                "Service": [
                  "lambda.amazonaws.com"
                ]
              },
              "Action": [
                "sts:AssumeRole"
              ]
            }
          ]
        },
        "Policies": [
          {
            "PolicyName": {
              "Fn::Join": [
                "-",
                [
                  "github",
                  "dev",
                  "lambda"
                ]
              ]
            },
            "PolicyDocument": {
              "Version": "2012-10-17",
              "Statement": [
                {
                  "Effect": "Allow",
                  "Action": [
                    "logs:CreateLogStream",
                    "logs:CreateLogGroup"
                  ],
                  "Resource": [
                    {
                      "Fn::Sub": "arn:${AWS::Partition}:logs:${AWS::Region}:${AWS::AccountId}:log-group:/aws/lambda/github-dev*:*"
                    }
                  ]
                },
                {
                  "Effect": "Allow",
                  "Action": [
                    "logs:PutLogEvents"
                  ],
                  "Resource": [
                    {
                      "Fn::Sub": "arn:${AWS::Partition}:logs:${AWS::Region}:${AWS::AccountId}:log-group:/aws/lambda/github-dev*:*:*"
                    }
                  ]
                }
              ]
            }
          }
        ],
        "Path": "/",
        "RoleName": {
          "Fn::Join": [
            "-",
            [
              "github",
              "dev",
              {
                "Ref": "AWS::Region"
              },
              "lambdaRole"
            ]
          ]
        }
      }
    },
    "RepositoryWatcherLambdaFunction": {
      "Type": "AWS::Lambda::Function",
      "Properties": {
        "Code": {
          "S3Bucket": {
            "Ref": "ServerlessDeploymentBucket"
          },
          "S3Key": "serverless/github/dev/1644790238458-2022-02-13T22:10:38.458Z/repositoryWatcher.zip"
        },
        "Handler": "src/functions/repositoryWatcher/handler.main",
        "Runtime": "nodejs14.x",
        "FunctionName": "github-dev-repositoryWatcher",
        "MemorySize": 1024,
        "Timeout": 6,
        "Environment": {
          "Variables": {
            "AWS_NODEJS_CONNECTION_REUSE_ENABLED": "1",
            "NODE_OPTIONS": "--enable-source-maps --stack-trace-limit=1000",
            "GITHUB_TOKEN": "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"
          }
        },
        "Role": {
          "Fn::GetAtt": [
            "IamRoleLambdaExecution",
            "Arn"
          ]
        }
      },
      "DependsOn": [
        "RepositoryWatcherLogGroup"
      ]
    },
    "RepositoryWatcherLambdaVersionws0pdoBSPTt8xY0K4PqcOVdu3LdS3xCWA3bw0IdBHAk": {
      "Type": "AWS::Lambda::Version",
      "DeletionPolicy": "Retain",
      "Properties": {
        "FunctionName": {
          "Ref": "RepositoryWatcherLambdaFunction"
        },
        "CodeSha256": "glx/tuuxVZWoLPvY8T2X2FmJXTdpwRKo4No//13oyDs="
      }
    },
    "ApiGatewayRestApi": {
      "Type": "AWS::ApiGateway::RestApi",
      "Properties": {
        "Name": "github-dev",
        "EndpointConfiguration": {
          "Types": [
            "EDGE"
          ]
        },
        "Policy": "",
        "MinimumCompressionSize": 1024
      }
    },
    "ApiGatewayResourceRepositorywatcher": {
      "Type": "AWS::ApiGateway::Resource",
      "Properties": {
        "ParentId": {
          "Fn::GetAtt": [
            "ApiGatewayRestApi",
            "RootResourceId"
          ]
        },
        "PathPart": "repositoryWatcher",
        "RestApiId": {
          "Ref": "ApiGatewayRestApi"
        }
      }
    },
    "ApiGatewayMethodRepositorywatcherPost": {
      "Type": "AWS::ApiGateway::Method",
      "Properties": {
        "HttpMethod": "POST",
        "RequestParameters": {},
        "ResourceId": {
          "Ref": "ApiGatewayResourceRepositorywatcher"
        },
        "RestApiId": {
          "Ref": "ApiGatewayRestApi"
        },
        "ApiKeyRequired": false,
        "AuthorizationType": "NONE",
        "Integration": {
          "IntegrationHttpMethod": "POST",
          "Type": "AWS_PROXY",
          "Uri": {
            "Fn::Join": [
              "",
              [
                "arn:",
                {
                  "Ref": "AWS::Partition"
                },
                ":apigateway:",
                {
                  "Ref": "AWS::Region"
                },
                ":lambda:path/2015-03-31/functions/",
                {
                  "Fn::GetAtt": [
                    "RepositoryWatcherLambdaFunction",
                    "Arn"
                  ]
                },
                "/invocations"
              ]
            ]
          }
        },
        "MethodResponses": [],
        "RequestValidatorId": {
          "Ref": "ApiGatewayGithubRequestValidator"
        },
        "RequestModels": {
          "application/json": {
            "Ref": "ApiGatewayMethodRepositorywatcherPostApplicationJsonModel"
          }
        }
      },
      "DependsOn": [
        "RepositoryWatcherLambdaPermissionApiGateway"
      ]
    },
    "ApiGatewayGithubRequestValidator": {
      "Type": "AWS::ApiGateway::RequestValidator",
      "Properties": {
        "RestApiId": {
          "Ref": "ApiGatewayRestApi"
        },
        "ValidateRequestBody": true,
        "ValidateRequestParameters": true,
        "Name": "github-dev | Validate request body and querystring parameters"
      }
    },
    "ApiGatewayMethodRepositorywatcherPostApplicationJsonModel": {
      "Type": "AWS::ApiGateway::Model",
      "Properties": {
        "RestApiId": {
          "Ref": "ApiGatewayRestApi"
        },
        "ContentType": "application/json",
        "Schema": {
          "type": "object",
          "properties": {
            "repository": {
              "type": "object",
              "properties": {
                "name": {
                  "type": "string"
                },
                "owner": {
                  "type": "object",
                  "properties": {
                    "login": {
                      "type": "string"
                    }
                  }
                }
              }
            },
            "sender": {
              "type": "object",
              "properties": {
                "login": {
                  "type": "string"
                },
                "id": {
                  "type": "number"
                }
              }
            }
          },
          "required": [
            "repository",
            "sender"
          ]
        }
      }
    },
    "ApiGatewayDeployment1644790237454": {
      "Type": "AWS::ApiGateway::Deployment",
      "Properties": {
        "RestApiId": {
          "Ref": "ApiGatewayRestApi"
        },
        "StageName": "dev"
      },
      "DependsOn": [
        "ApiGatewayMethodRepositorywatcherPost"
      ]
    },
    "RepositoryWatcherLambdaPermissionApiGateway": {
      "Type": "AWS::Lambda::Permission",
      "Properties": {
        "FunctionName": {
          "Fn::GetAtt": [
            "RepositoryWatcherLambdaFunction",
            "Arn"
          ]
        },
        "Action": "lambda:InvokeFunction",
        "Principal": "apigateway.amazonaws.com",
        "SourceArn": {
          "Fn::Join": [
            "",
            [
              "arn:",
              {
                "Ref": "AWS::Partition"
              },
              ":execute-api:",
              {
                "Ref": "AWS::Region"
              },
              ":",
              {
                "Ref": "AWS::AccountId"
              },
              ":",
              {
                "Ref": "ApiGatewayRestApi"
              },
              "/*/*"
            ]
          ]
        }
      }
    }
  },
  "Outputs": {
    "ServerlessDeploymentBucketName": {
      "Value": {
        "Ref": "ServerlessDeploymentBucket"
      },
      "Export": {
        "Name": "sls-github-dev-ServerlessDeploymentBucketName"
      }
    },
    "RepositoryWatcherLambdaFunctionQualifiedArn": {
      "Description": "Current Lambda function version",
      "Value": {
        "Ref": "RepositoryWatcherLambdaVersionws0pdoBSPTt8xY0K4PqcOVdu3LdS3xCWA3bw0IdBHAk"
      },
      "Export": {
        "Name": "sls-github-dev-RepositoryWatcherLambdaFunctionQualifiedArn"
      }
    },
    "ServiceEndpoint": {
      "Description": "URL of the service endpoint",
      "Value": {
        "Fn::Join": [
          "",
          [
            "https://",
            {
              "Ref": "ApiGatewayRestApi"
            },
            ".execute-api.",
            {
              "Ref": "AWS::Region"
            },
            ".",
            {
              "Ref": "AWS::URLSuffix"
            },
            "/dev"
          ]
        ]
      },
      "Export": {
        "Name": "sls-github-dev-ServiceEndpoint"
      }
    }
  }
}